aping.py
aping/__init__.py
aping/main.py
aping/ping.py
aping_cli-0.2.0.dist-info/LICENSE
aping_cli-0.2.0.dist-info/METADATA
aping_cli-0.2.0.dist-info/WHEEL
aping_cli-0.2.0.dist-info/entry_points.txt
aping_cli-0.2.0.dist-info/top_level.txt
aping_cli-0.2.0.dist-info/RECORD
