Metadata-Version: 2.1
Name: aping-cli
Version: 0.2.0
Summary: A tool to ping multiple hosts at once and export results as Prometheus metrics.
Home-page: https://github.com/alexpizarroj/aping
Author: Alex Pizarro
Author-email: alex.pizarro.j@gmail.com
License: MIT
Platform: UNKNOWN
Classifier: License :: OSI Approved :: MIT License
Classifier: Programming Language :: Python :: 3
Classifier: Programming Language :: Python :: 3 :: Only
Classifier: Programming Language :: Python :: 3.7
Classifier: Programming Language :: Python :: 3.8
Classifier: Programming Language :: Python :: 3.9
Classifier: Programming Language :: Python :: 3.10
Classifier: Programming Language :: Python :: 3.11
Requires-Python: >=3.7
Requires-Dist: multiping (==1.1.2)
Requires-Dist: prometheus-client (==0.16.0)
